Workbook
Name NativeTimeline_Date: #N/A

Sheet RAW_DATA
A1: Segment | B1: Country | C1: Product | D1: Discount Band | E1: Units Sold | F1: Manufacturing Price | G1: Sale Price | H1: Gross Sales | I1: Discounts | J1: Sales | K1: COGS | L1: Profit | M1: Date | N1: Month Number | O1: Month Name | P1: Year
A2: Government | B2: Canada | C2: Carretera | D2: None | E2: 1618.5 | F2: 3 | G2: 20 | H2: 32370 | I2: 0 | J2: 32370 | K2: 16185 | L2: 16185 | M2: 41640 | N2: 1 | O2: January | P2: 2014 | R2: ⚠️ DO NOT MODIFY — SOURCE DATA ONLY
A3: Government | B3: Germany | C3: Carretera | D3: None | E3: 1321 | F3: 3 | G3: 20 | H3: 26420 | I3: 0 | J3: 26420 | K3: 13210 | L3: 13210 | M3: 41640 | N3: 1 | O3: January | P3: 2014
A4: Midmarket | B4: France | C4: Carretera | D4: None | E4: 2178 | F4: 3 | G4: 15 | H4: 32670 | I4: 0 | J4: 32670 | K4: 21780 | L4: 10890 | M4: 41791 | N4: 6 | O4: June | P4: 2014
A5: Midmarket | B5: Germany | C5: Carretera | D5: None | E5: 888 | F5: 3 | G5: 15 | H5: 13320 | I5: 0 | J5: 13320 | K5: 8880 | L5: 4440 | M5: 41791 | N5: 6 | O5: June | P5: 2014
A6: Midmarket | B6: Mexico | C6: Carretera | D6: None | E6: 2470 | F6: 3 | G6: 15 | H6: 37050 | I6: 0 | J6: 37050 | K6: 24700 | L6: 12350 | M6: 41791 | N6: 6 | O6: June | P6: 2014
A7: Government | B7: Germany | C7: Carretera | D7: None | E7: 1513 | F7: 3 | G7: 350 | H7: 529550 | I7: 0 | J7: 529550 | K7: 393380 | L7: 136170 | M7: 41974 | N7: 12 | O7: December | P7: 2014
A8: Midmarket | B8: Germany | C8: Montana | D8: None | E8: 921 | F8: 5 | G8: 15 | H8: 13815 | I8: 0 | J8: 13815 | K8: 9210 | L8: 4605 | M8: 41699 | N8: 3 | O8: March | P8: 2014
A9: Channel Partners | B9: Canada | C9: Montana | D9: None | E9: 2518 | F9: 5 | G9: 12 | H9: 30216 | I9: 0 | J9: 30216 | K9: 7554 | L9: 22662 | M9: 41791 | N9: 6 | O9: June | P9: 2014
A10: Government | B10: France | C10: Montana | D10: None | E10: 1899 | F10: 5 | G10: 20 | H10: 37980 | I10: 0 | J10: 37980 | K10: 18990 | L10: 18990 | M10: 41791 | N10: 6 | O10: June | P10: 2014
A11: Channel Partners | B11: Germany | C11: Montana | D11: None | E11: 1545 | F11: 5 | G11: 12 | H11: 18540 | I11: 0 | J11: 18540 | K11: 4635 | L11: 13905 | M11: 41791 | N11: 6 | O11: June | P11: 2014
A12: Midmarket | B12: Mexico | C12: Montana | D12: None | E12: 2470 | F12: 5 | G12: 15 | H12: 37050 | I12: 0 | J12: 37050 | K12: 24700 | L12: 12350 | M12: 41791 | N12: 6 | O12: June | P12: 2014
A13: Enterprise | B13: Canada | C13: Montana | D13: None | E13: 2665.5 | F13: 5 | G13: 125 | H13: 333187.5 | I13: 0 | J13: 333187.5 | K13: 319860 | L13: 13327.5 | M13: 41821 | N13: 7 | O13: July | P13: 2014
A14: Small Business | B14: Mexico | C14: Montana | D14: None | E14: 958 | F14: 5 | G14: 300 | H14: 287400 | I14: 0 | J14: 287400 | K14: 239500 | L14: 47900 | M14: 41852 | N14: 8 | O14: August | P14: 2014
... A701: Channel Partners | B701: United States of America | C701: VTT | D701: High | E701: 1806 | F701: 250 | G701: 12 | H701: 21672 | I701: 3250.8 | J701: 18421.2 | K701: 5418 | L701: 13003.2 | M701: 41760 | N701: 5 | O701: May | P701: 2014

Sheet CLEANED_DATA
A1: Segment | B1: Country | C1: Product | D1: Discount Band | E1: Units Sold | F1: Manufacturing Price | G1: Sale Price | H1: Gross Sales | I1: Discounts | J1: Sales | K1: COGS | L1: Profit | M1: Date | N1: Month Number | O1: Month Name | P1: Year | Q1: Profit_Margin_% | R1: Discount_Pct | S1: Sales_Category | T1: COGS_Pct | U1: Profit_Flag
A2: Government | B2: Canada | C2: Carretera | D2: None | E2: 1618.5 | F2: 3 | G2: 20 | H2: 32370 | I2: 0 | J2: 32370 | K2: 16185 | L2: 16185 | M2: 41640 | N2: 1 | O2: January | P2: 2014 | Q2: =IF(J2=0,0,L2/J2) -> 0.5 | R2: =IF(H2=0,0, I2/H2) -> 0 | S2: =IF(J2<10000,"Small",IF(J2<50000,"Medium",IF(J2<200000,"Large","Enterprise"))) -> Medium | T2: =IF(J2=0,0,K2/J2) -> 0.5 | U2: =IFERROR(IF(L2>0,"Profitable ✅",IF(L2=0,"Breakeven ⚖️","Loss ❌")),"Check Data 📊") -> Profitable ✅
A3: Government | B3: Germany | C3: Carretera | D3: None | E3: 1321 | F3: 3 | G3: 20 | H3: 26420 | I3: 0 | J3: 26420 | K3: 13210 | L3: 13210 | M3: 41640 | N3: 1 | O3: January | P3: 2014 | Q3: =IF(J3=0,0,L3/J3) -> 0.5 | R3: =IF(H3=0,0, I3/H3) -> 0 | S3: =IF(J3<10000,"Small",IF(J3<50000,"Medium",IF(J3<200000,"Large","Enterprise"))) -> Medium | T3: =IF(J3=0,0,K3/J3) -> 0.5 | U3: =IFERROR(IF(L3>0,"Profitable ✅",IF(L3=0,"Breakeven ⚖️","Loss ❌")),"Check Data 📊") -> Profitable ✅
A4: Midmarket | B4: France | C4: Carretera | D4: None | E4: 2178 | F4: 3 | G4: 15 | H4: 32670 | I4: 0 | J4: 32670 | K4: 21780 | L4: 10890 | M4: 41791 | N4: 6 | O4: June | P4: 2014 | Q4: =IF(J4=0,0,L4/J4) -> 0.33333333 | R4: =IF(H4=0,0, I4/H4) -> 0 | S4: =IF(J4<10000,"Small",IF(J4<50000,"Medium",IF(J4<200000,"Large","Enterprise"))) -> Medium | T4: =IF(J4=0,0,K4/J4) -> 0.66666667 | U4: =IFERROR(IF(L4>0,"Profitable ✅",IF(L4=0,"Breakeven ⚖️","Loss ❌")),"Check Data 📊") -> Profitable ✅
A5: Midmarket | B5: Germany | C5: Carretera | D5: None | E5: 888 | F5: 3 | G5: 15 | H5: 13320 | I5: 0 | J5: 13320 | K5: 8880 | L5: 4440 | M5: 41791 | N5: 6 | O5: June | P5: 2014 | Q5: =IF(J5=0,0,L5/J5) -> 0.33333333 | R5: =IF(H5=0,0, I5/H5) -> 0 | S5: =IF(J5<10000,"Small",IF(J5<50000,"Medium",IF(J5<200000,"Large","Enterprise"))) -> Medium | T5: =IF(J5=0,0,K5/J5) -> 0.66666667 | U5: =IFERROR(IF(L5>0,"Profitable ✅",IF(L5=0,"Breakeven ⚖️","Loss ❌")),"Check Data 📊") -> Profitable ✅
A6: Midmarket | B6: Mexico | C6: Carretera | D6: None | E6: 2470 | F6: 3 | G6: 15 | H6: 37050 | I6: 0 | J6: 37050 | K6: 24700 | L6: 12350 | M6: 41791 | N6: 6 | O6: June | P6: 2014 | Q6: =IF(J6=0,0,L6/J6) -> 0.33333333 | R6: =IF(H6=0,0, I6/H6) -> 0 | S6: =IF(J6<10000,"Small",IF(J6<50000,"Medium",IF(J6<200000,"Large","Enterprise"))) -> Medium | T6: =IF(J6=0,0,K6/J6) -> 0.66666667 | U6: =IFERROR(IF(L6>0,"Profitable ✅",IF(L6=0,"Breakeven ⚖️","Loss ❌")),"Check Data 📊") -> Profitable ✅
A7: Government | B7: Germany | C7: Carretera | D7: None | E7: 1513 | F7: 3 | G7: 350 | H7: 529550 | I7: 0 | J7: 529550 | K7: 393380 | L7: 136170 | M7: 41974 | N7: 12 | O7: December | P7: 2014 | Q7: =IF(J7=0,0,L7/J7) -> 0.25714286 | R7: =IF(H7=0,0, I7/H7) -> 0 | S7: =IF(J7<10000,"Small",IF(J7<50000,"Medium",IF(J7<200000,"Large","Enterprise"))) -> Enterprise | T7: =IF(J7=0,0,K7/J7) -> 0.74285714 | U7: =IFERROR(IF(L7>0,"Profitable ✅",IF(L7=0,"Breakeven ⚖️","Loss ❌")),"Check Data 📊") -> Profitable ✅
A8: Midmarket | B8: Germany | C8: Montana | D8: None | E8: 921 | F8: 5 | G8: 15 | H8: 13815 | I8: 0 | J8: 13815 | K8: 9210 | L8: 4605 | M8: 41699 | N8: 3 | O8: March | P8: 2014 | Q8: =IF(J8=0,0,L8/J8) -> 0.33333333 | R8: =IF(H8=0,0, I8/H8) -> 0 | S8: =IF(J8<10000,"Small",IF(J8<50000,"Medium",IF(J8<200000,"Large","Enterprise"))) -> Medium | T8: =IF(J8=0,0,K8/J8) -> 0.66666667 | U8: =IFERROR(IF(L8>0,"Profitable ✅",IF(L8=0,"Breakeven ⚖️","Loss ❌")),"Check Data 📊") -> Profitable ✅
A9: Channel Partners | B9: Canada | C9: Montana | D9: None | E9: 2518 | F9: 5 | G9: 12 | H9: 30216 | I9: 0 | J9: 30216 | K9: 7554 | L9: 22662 | M9: 41791 | N9: 6 | O9: June | P9: 2014 | Q9: =IF(J9=0,0,L9/J9) -> 0.75 | R9: =IF(H9=0,0, I9/H9) -> 0 | S9: =IF(J9<10000,"Small",IF(J9<50000,"Medium",IF(J9<200000,"Large","Enterprise"))) -> Medium | T9: =IF(J9=0,0,K9/J9) -> 0.25 | U9: =IFERROR(IF(L9>0,"Profitable ✅",IF(L9=0,"Breakeven ⚖️","Loss ❌")),"Check Data 📊") -> Profitable ✅
A10: Government | B10: France | C10: Montana | D10: None | E10: 1899 | F10: 5 | G10: 20 | H10: 37980 | I10: 0 | J10: 37980 | K10: 18990 | L10: 18990 | M10: 41791 | N10: 6 | O10: June | P10: 2014 | Q10: =IF(J10=0,0,L10/J10) -> 0.5 | R10: =IF(H10=0,0, I10/H10) -> 0 | S10: =IF(J10<10000,"Small",IF(J10<50000,"Medium",IF(J10<200000,"Large","Enterprise"))) -> Medium | T10: =IF(J10=0,0,K10/J10) -> 0.5 | U10: =IFERROR(IF(L10>0,"Profitable ✅",IF(L10=0,"Breakeven ⚖️","Loss ❌")),"Check Data 📊") -> Profitable ✅
A11: Channel Partners | B11: Germany | C11: Montana | D11: None | E11: 1545 | F11: 5 | G11: 12 | H11: 18540 | I11: 0 | J11: 18540 | K11: 4635 | L11: 13905 | M11: 41791 | N11: 6 | O11: June | P11: 2014 | Q11: =IF(J11=0,0,L11/J11) -> 0.75 | R11: =IF(H11=0,0, I11/H11) -> 0 | S11: =IF(J11<10000,"Small",IF(J11<50000,"Medium",IF(J11<200000,"Large","Enterprise"))) -> Medium | T11: =IF(J11=0,0,K11/J11) -> 0.25 | U11: =IFERROR(IF(L11>0,"Profitable ✅",IF(L11=0,"Breakeven ⚖️","Loss ❌")),"Check Data 📊") -> Profitable ✅
A12: Midmarket | B12: Mexico | C12: Montana | D12: None | E12: 2470 | F12: 5 | G12: 15 | H12: 37050 | I12: 0 | J12: 37050 | K12: 24700 | L12: 12350 | M12: 41791 | N12: 6 | O12: June | P12: 2014 | Q12: =IF(J12=0,0,L12/J12) -> 0.33333333 | R12: =IF(H12=0,0, I12/H12) -> 0 | S12: =IF(J12<10000,"Small",IF(J12<50000,"Medium",IF(J12<200000,"Large","Enterprise"))) -> Medium | T12: =IF(J12=0,0,K12/J12) -> 0.66666667 | U12: =IFERROR(IF(L12>0,"Profitable ✅",IF(L12=0,"Breakeven ⚖️","Loss ❌")),"Check Data 📊") -> Profitable ✅
A13: Enterprise | B13: Canada | C13: Montana | D13: None | E13: 2665.5 | F13: 5 | G13: 125 | H13: 333187.5 | I13: 0 | J13: 333187.5 | K13: 319860 | L13: 13327.5 | M13: 41821 | N13: 7 | O13: July | P13: 2014 | Q13: =IF(J13=0,0,L13/J13) -> 0.04 | R13: =IF(H13=0,0, I13/H13) -> 0 | S13: =IF(J13<10000,"Small",IF(J13<50000,"Medium",IF(J13<200000,"Large","Enterprise"))) -> Enterprise | T13: =IF(J13=0,0,K13/J13) -> 0.96 | U13: =IFERROR(IF(L13>0,"Profitable ✅",IF(L13=0,"Breakeven ⚖️","Loss ❌")),"Check Data 📊") -> Profitable ✅
... A701: Channel Partners | B701: United States of America | C701: VTT | D701: High | E701: 1806 | F701: 250 | G701: 12 | H701: 21672 | I701: 3250.8 | J701: 18421.2 | K701: 5418 | L701: 13003.2 | M701: 41760 | N701: 5 | O701: May | P701: 2014 | Q701: =IF(J701=0,0,L701/J701) -> 0.70588235 | R701: =IF(H701=0,0, I701/H701) -> 0.15 | S701: =IF(J701<10000,"Small",IF(J701<50000,"Medium",IF(J701<200000,"Large","Enterprise"))) -> Medium | T701: =IF(J701=0,0,K701/J701) -> 0.29411765 | U701: =IFERROR(IF(L701>0,"Profitable ✅",IF(L701=0,"Breakeven ⚖️","Loss ❌")),"Check Data 📊") -> Profitable ✅

Sheet KPI_SUMMARY
B2: OVERALL FINANCIAL KPIs — GlobalPeak Corp (2013-2014)
B3: KPI Metric | C3: Formula Used | D3: Value | E3: Business Meaning
B4: Total Gross Sales | C4: =SUM(CLEANED_DATA!H:H) | D4: =SUM(CLEANED_DATA!H2:H701) -> 1.279316e+08 | E4: Revenue before discounts — top line number
B5: Total Discounts Given | C5: =SUM(CLEANED_DATA!I:I) | D5: =SUM(CLEANED_DATA!I2:I701) -> 9205248.2 | E5: Total discount amount — reduces gross to net sales
B6: Total Net Sales | C6: =SUM(CLEANED_DATA!J:J) | D6: =SUM(CLEANED_DATA!J2:J701) -> 1.1872635e+08 | E6: Actual revenue after discounts — core revenue metric
B7: Total COGS | C7: =SUM(CLEANED_DATA!K:K) | D7: =SUM(CLEANED_DATA!K2:K701) -> 101832648 | E7: Cost of Goods Sold — direct cost of making products
B8: Total Profit | C8: =SUM(CLEANED_DATA!L:L) | D8: =SUM(CLEANED_DATA!L2:L701) -> 16893702 | E8: Net profit after all costs — bottom line number
B9: Overall Profit Margin % | C9: =SUM(L:L)/SUM(J:J) | D9: =IF(D6=0,0, D8/D6) -> 0.14229109 | E9: Profit ÷ Net Sales — efficiency of business
B10: Total Units Sold | C10: =SUM(CLEANED_DATA!E:E) | D10: =SUM(CLEANED_DATA!E2:E701) -> 1125806 | E10: Total product units sold across all markets
B13: PERFORMANCE BY SEGMENT — SUMIF Analysis
B14: Segment | C14: Net Sales | D14: % of Total | E14: Total Profit | F14: Profit Margin | G14: Total COGS | H14: Units Sold
B15: Channer Partners | C15: =SUMIF(CLEANED_DATA!A2:A701,"Channel Partners",CLEANED_DATA!J2:J701) -> 1800593.6 | D15: =C15/$D$6 -> 0.015165914 | E15: =SUMIF(CLEANED_DATA!A2:A701,"Channel Partners",CLEANED_DATA!L2:L701) -> 1316803.1 | F15: =IF(C15=0,0,E15/C15) -> 0.73131611 | G15: =SUMIF(CLEANED_DATA!A2:A701,"Channel Partners",CLEANED_DATA!K2:K701) -> 483790.5 | H15: =SUMIF(CLEANED_DATA!A2:A701,"Channel Partners",CLEANED_DATA!E2:E701) -> 161263.5
B16: Mid Market | C16: =SUMIF(CLEANED_DATA!A2:A701,"Midmarket",CLEANED_DATA!J2:J701) -> 2381883.1 | D16: =C16/$D$6 -> 0.020061958 | E16: =SUMIF(CLEANED_DATA!A2:A701,"Midmarket",CLEANED_DATA!L2:L701) -> 660103.07 | F16: =IF(C16=0,0,E16/C16) -> 0.27713496 | G16: =SUMIF(CLEANED_DATA!A2:A701,"Midmarket",CLEANED_DATA!K2:K701) -> 1721780 | H16: =SUMIF(CLEANED_DATA!A2:A701,"Midmarket",CLEANED_DATA!E2:E701) -> 172178
B17: Enterprise | C17: =SUMIF(CLEANED_DATA!A2:A701,"Enterprise",CLEANED_DATA!J2:J701) -> 19611694 | D17: =C17/$D$6 -> 0.16518401 | E17: =SUMIF(CLEANED_DATA!A2:A701,"Enterprise",CLEANED_DATA!L2:L701) -> -614545.62 | F17: =IF(C17=0,0,E17/C17) -> -0.031335672 | G17: =SUMIF(CLEANED_DATA!A2:A701,"Enterprise",CLEANED_DATA!K2:K701) -> 20226240 | H17: =SUMIF(CLEANED_DATA!A2:A701,"Enterprise",CLEANED_DATA!E2:E701) -> 168552
B18: Small Business | C18: =SUMIF(CLEANED_DATA!A2:A701,"Small Business",CLEANED_DATA!J2:J701) -> 42427918 | D18: =C18/$D$6 -> 0.3573589 | E18: =SUMIF(CLEANED_DATA!A2:A701,"Small Business",CLEANED_DATA!L2:L701) -> 4143168.5 | F18: =IF(C18=0,0,E18/C18) -> 0.097651939 | G18: =SUMIF(CLEANED_DATA!A2:A701,"Small Business",CLEANED_DATA!K2:K701) -> 38284750 | H18: =SUMIF(CLEANED_DATA!A2:A701,"Small Business",CLEANED_DATA!E2:E701) -> 153139
B19: Government | C19: =SUMIF(CLEANED_DATA!A2:A701, "Government", CLEANED_DATA!J2:J701) -> 52504261 | D19: =C19/$D$6 -> 0.44222921 | E19: =SUMIF(CLEANED_DATA!A2:A701,"Government",CLEANED_DATA!L2:L701) -> 11388173 | F19: =IF(C19=0,0,E19/C19) -> 0.21689998 | G19: =SUMIF(CLEANED_DATA!A2:A701,"Government",CLEANED_DATA!K2:K701) -> 41116088 | H19: =SUMIF(CLEANED_DATA!A2:A701,"Government",CLEANED_DATA!E2:E701) -> 470673.5
B20: Total | C20: =SUM(C15:C19) -> 1.1872635e+08 | D20: =C20/$D$6 -> 1 | E20: =SUM(E15:E19) -> 16893702 | F20: =IF(C20=0,0,E20/C20) -> 0.14229109 | G20: =SUM(G15:G19) -> 101832648 | H20: =SUM(H15:H19) -> 1125806
B23: PERFORMANCE BY COUNTRY — SUMIF Analysis
B24: Country | C24: Net Sales | D24: % of Total | E24: Total Profit | F24: Profit Margin | G24: Total COGS | H24: Units Sold
B25: Canada | C25: =SUMIF(CLEANED_DATA!B2:B701,"Canada",CLEANED_DATA!J2:J701) -> 24887655 | D25: =C25/$D$6 -> 0.209622 | E25: =SUMIF(CLEANED_DATA!B2:B701,"Canada",CLEANED_DATA!L2:L701) -> 3529228.9 | F25: =IF(C25=0,0, E25/C25) -> 0.14180641 | G25: =SUMIF(CLEANED_DATA!B2:B701,"Canada",CLEANED_DATA!K2:K701) -> 21358426 | H25: =SUMIF(CLEANED_DATA!B2:B701,"Canada",CLEANED_DATA!E2:E701) -> 247428.5
B26: Germany | C26: =SUMIF(CLEANED_DATA!B2:B701,"Germany",CLEANED_DATA!J2:J701) -> 23505341 | D26: =C26/$D$6 -> 0.19797914 | E26: =SUMIF(CLEANED_DATA!B2:B701,"Germany",CLEANED_DATA!L2:L701) -> 3680388.8 | F26: =IF(C26=0,0, E26/C26) -> 0.15657671 | G26: =SUMIF(CLEANED_DATA!B2:B701,"Germany",CLEANED_DATA!K2:K701) -> 19824952 | H26: =SUMIF(CLEANED_DATA!B2:B701,"Germany",CLEANED_DATA!E2:E701) -> 201494
B27: France | C27: =SUMIF(CLEANED_DATA!B2:B701,"France",CLEANED_DATA!J2:J701) -> 24354172 | D27: =C27/$D$6 -> 0.20512862 | E27: =SUMIF(CLEANED_DATA!B2:B701,"France",CLEANED_DATA!L2:L701) -> 3781020.8 | F27: =IF(C27=0,0, E27/C27) -> 0.15525146 | G27: =SUMIF(CLEANED_DATA!B2:B701,"France",CLEANED_DATA!K2:K701) -> 20573152 | H27: =SUMIF(CLEANED_DATA!B2:B701,"France",CLEANED_DATA!E2:E701) -> 240931
B28: Mexico | C28: =SUMIF(CLEANED_DATA!B2:B701,"Mexico",CLEANED_DATA!J2:J701) -> 20949352 | D28: =C28/$D$6 -> 0.17645074 | E28: =SUMIF(CLEANED_DATA!B2:B701,"Mexico",CLEANED_DATA!L2:L701) -> 2907523.1 | F28: =IF(C28=0,0, E28/C28) -> 0.13878821 | G28: =SUMIF(CLEANED_DATA!B2:B701,"Mexico",CLEANED_DATA!K2:K701) -> 18041829 | H28: =SUMIF(CLEANED_DATA!B2:B701,"Mexico",CLEANED_DATA!E2:E701) -> 203325
B29: United States of America | C29: =SUMIF(CLEANED_DATA!B2:B701,"United States of America",CLEANED_DATA!J2:J701) -> 25029830 | D29: =C29/$D$6 -> 0.2108195 | E29: =SUMIF(CLEANED_DATA!B2:B701,"United States of America",CLEANED_DATA!L2:L701) -> 2995540.7 | F29: =IF(C29=0,0, E29/C29) -> 0.11967883 | G29: =SUMIF(CLEANED_DATA!B2:B701,"United States of America",CLEANED_DATA!K2:K701) -> 22034290 | H29: =SUMIF(CLEANED_DATA!B2:B701,"United States of America",CLEANED_DATA!E2:E701) -> 232627.5
B30: Total | C30: =SUM(C25:C29) -> 1.1872635e+08 | D30: =C30/$D$6 -> 1 | E30: =SUM(E25:E29) -> 16893702 | F30: =IF(C30=0,0, E30/C30) -> 0.14229109 | G30: =SUM(G25:G29) -> 101832648 | H30: =SUM(H25:H29) -> 1125806
B33: PERFORMANCE BY PRODUCT — SUMIF Analysis
B34: Product | C34: Net Sales | D34: % of Total | E34: Total Profit | F34: Profit Margin | G34: Total COGS | H34: Units Sold
B35: Paseo | C35: =SUMIF(CLEANED_DATA!C2:C701,"Paseo",CLEANED_DATA!J2:J701) -> 33011144 | D35: =C35/$D$6 -> 0.27804395 | E35: =SUMIF(CLEANED_DATA!C2:C701,"Paseo",CLEANED_DATA!L2:L701) -> 4797437.9 | F35: =IF(C35=0,0,E35/C35) -> 0.14532783 | G35: =SUMIF(CLEANED_DATA!C2:C701,"Paseo",CLEANED_DATA!K2:K701) -> 28213706 | H35: =SUMIF(CLEANED_DATA!C2:C701,"Paseo",CLEANED_DATA!E2:E701) -> 338239.5
B36: VTT | C36: =SUMIF(CLEANED_DATA!C2:C701,"VTT",CLEANED_DATA!J2:J701) -> 20511921 | D36: =C36/$D$6 -> 0.17276637 | E36: =SUMIF(CLEANED_DATA!C2:C701,"VTT",CLEANED_DATA!L2:L701) -> 3034608 | F36: =IF(C36=0,0,E36/C36) -> 0.14794363 | G36: =SUMIF(CLEANED_DATA!C2:C701,"VTT",CLEANED_DATA!K2:K701) -> 17477313 | H36: =SUMIF(CLEANED_DATA!C2:C701,"VTT",CLEANED_DATA!E2:E701) -> 168783
B37: Velo | C37: =SUMIF(CLEANED_DATA!C2:C701,"Velo",CLEANED_DATA!J2:J701) -> 18250059 | D37: =C37/$D$6 -> 0.15371532 | E37: =SUMIF(CLEANED_DATA!C2:C701,"Velo",CLEANED_DATA!L2:L701) -> 2305992.5 | F37: =IF(C37=0,0,E37/C37) -> 0.12635534 | G37: =SUMIF(CLEANED_DATA!C2:C701,"Velo",CLEANED_DATA!K2:K701) -> 15944067 | H37: =SUMIF(CLEANED_DATA!C2:C701,"Velo",CLEANED_DATA!E2:E701) -> 162424.5
B38: Amarilla | C38: =SUMIF(CLEANED_DATA!C2:C701,"Amarilla",CLEANED_DATA!J2:J701) -> 17747116 | D38: =C38/$D$6 -> 0.14947917 | E38: =SUMIF(CLEANED_DATA!C2:C701,"Amarilla",CLEANED_DATA!L2:L701) -> 2814104.1 | F38: =IF(C38=0,0,E38/C38) -> 0.15856684 | G38: =SUMIF(CLEANED_DATA!C2:C701,"Amarilla",CLEANED_DATA!K2:K701) -> 14933012 | H38: =SUMIF(CLEANED_DATA!C2:C701,"Amarilla",CLEANED_DATA!E2:E701) -> 155315
B39: Montana | C39: =SUMIF(CLEANED_DATA!C2:C701,"Montana",CLEANED_DATA!J2:J701) -> 15390802 | D39: =C39/$D$6 -> 0.12963257 | E39: =SUMIF(CLEANED_DATA!C2:C701,"Montana",CLEANED_DATA!L2:L701) -> 2114754.9 | F39: =IF(C39=0,0,E39/C39) -> 0.13740381 | G39: =SUMIF(CLEANED_DATA!C2:C701,"Montana",CLEANED_DATA!K2:K701) -> 13276047 | H39: =SUMIF(CLEANED_DATA!C2:C701,"Montana",CLEANED_DATA!E2:E701) -> 154198
B40: Carretera | C40: =SUMIF(CLEANED_DATA!C2:C701,"Carretera",CLEANED_DATA!J2:J701) -> 13815308 | D40: =C40/$D$6 -> 0.11636261 | E40: =SUMIF(CLEANED_DATA!C2:C701,"Carretera",CLEANED_DATA!L2:L701) -> 1826804.9 | F40: =IF(C40=0,0,E40/C40) -> 0.13223049 | G40: =SUMIF(CLEANED_DATA!C2:C701,"Carretera",CLEANED_DATA!K2:K701) -> 11988503 | H40: =SUMIF(CLEANED_DATA!C2:C701,"Carretera",CLEANED_DATA!E2:E701) -> 146846
B41: Total | C41: =SUM(C35:C40) -> 1.1872635e+08 | D41: =C41/$D$6 -> 1 | E41: =SUM(E35:E40) -> 16893702 | F41: =IF(C41=0,0,E41/C41) -> 0.14229109 | G41: =SUM(G35:G40) -> 101832648 | H41: =SUM(H35:H40) -> 1125806
B44: PERFORMANCE BY YEAR — SUMIF Analysis
B45: Year | C45: Net Sales | D45: % of Total | E45: Total Profit | F45: Profit Margin | G45: Total COGS | H45: Units Sold
B46: 2013 | C46: =SUMIF(CLEANED_DATA!P2:P701,2013,CLEANED_DATA!J2:J701) -> 26415256 | D46: =C46/$D$6 -> 0.22248857 | E46: =SUMIF(CLEANED_DATA!P2:P701,2013,CLEANED_DATA!L2:L701) -> 3878464.5 | F46: =IF(C46=0,0,E46/C46) -> 0.14682669 | G46: =SUMIF(CLEANED_DATA!P2:P701,2013,CLEANED_DATA!K2:K701) -> 22536791 | H46: =SUMIF(CLEANED_DATA!P2:P701,2013,CLEANED_DATA!E2:E701) -> 264674
B47: 2014 | C47: =SUMIF(CLEANED_DATA!P2:P701,2014,CLEANED_DATA!J2:J701) -> 92311095 | D47: =C47/$D$6 -> 0.77751143 | E47: =SUMIF(CLEANED_DATA!P2:P701,2014,CLEANED_DATA!L2:L701) -> 13015238 | F47: =IF(C47=0,0,E47/C47) -> 0.14099321 | G47: =SUMIF(CLEANED_DATA!P2:P701,2014,CLEANED_DATA!K2:K701) -> 79295857 | H47: =SUMIF(CLEANED_DATA!P2:P701,2014,CLEANED_DATA!E2:E701) -> 861132
B48: Total | C48: =SUM(C46:C47) -> 1.1872635e+08 | D48: =C48/$D$6 -> 1 | E48: =SUM(E46:E47) -> 16893702 | F48: =IF(C48=0,0,E48/C48) -> 0.14229109 | G48: =SUM(G46:G47) -> 101832648 | H48: =SUM(H46:H47) -> 1125806

Sheet PIVOT_ANALYSIS
B1: PIVOT ANALYSIS SECTION
B3: SEGMENT × YEAR SALES MATRIX
B4: Total Sales | C4: Year
B5: Segment | C5: 2013 | D5: 2014 | E5: Total
B6: Channel Partners | C6: 398090.28 | D6: 1402503.4 | E6: 1800593.6
B7: Enterprise | C7: 4049562.5 | D7: 15562132 | E7: 19611694
B8: Government | C8: 13085685 | D8: 39418575 | E8: 52504261
B9: Midmarket | C9: 546243.45 | D9: 1835639.6 | E9: 2381883.1
B10: Small Business | C10: 8335674 | D10: 34092244 | E10: 42427918
B11: Total | C11: 26415256 | D11: 92311095 | E11: 1.1872635e+08
B13: PRODUCT × COUNTRY PROFIT MATRIX
C14: Country
B15: Product | C15: Canada | D15: France | E15: Germany | F15: Mexico | G15: United States of America | H15: Grand Total
B16: Amarilla | C16: 646861.38 | D16: 667867.63 | E16: 612137.26 | F16: 498611.39 | G16: 388626.4 | H16: 2814104.1
B17: Carretera | C17: 436105.34 | D17: 388864.9 | E17: 369674.68 | F17: 393668.42 | G17: 238491.55 | H17: 1826804.9
B18: Montana | C18: 321867.03 | D18: 461238.37 | E18: 559438.37 | F18: 337689.31 | G18: 434521.8 | H18: 2114754.9
B19: Paseo | C19: 1265018 | D19: 838748.56 | E19: 744416.74 | F19: 928651.39 | G19: 1020603.3 | H19: 4797438
B20: Velo | C20: 370568.34 | D20: 707930.23 | E20: 788789 | F20: 173303.89 | G20: 265401 | H20: 2305992.5
B21: VTT | C21: 488808.81 | D21: 716371.09 | E21: 605932.77 | F21: 575598.71 | G21: 647896.64 | H21: 3034608
B22: Grand Total | C22: 3529228.9 | D22: 3781020.8 | E22: 3680388.8 | F22: 2907523.1 | G22: 2995540.7 | H22: 16893702
B33: DISCOUNT BAND ANALYSIS + TIMELINE SLICER
B34: Discount | C34: Sum of Sales | D34: Sum of Profit | E34: Profit Margin %
B35: None | C35: 7943654 | D35: 1736455 | E35: =IF(C35=0,0,D35/C35) -> 0.2185965
B36: Low | C36: 34629779 | D36: 6188857.7 | E36: =IF(C36=0,0,D36/C36) -> 0.17871491
B37: Medium | C37: 38780431 | D37: 5579522.8 | E37: =IF(C37=0,0,D37/C37) -> 0.1438747
B38: High | C38: 37372487 | D38: 3388866.7 | E38: =IF(C38=0,0,D38/C38) -> 0.090678117
B39: Grand Total | C39: 1.1872635e+08 | D39: 16893702 | E39: =IF(C39=0,0,D39/C39) -> 0.14229109

Sheet DASHBOARD
B1: GlobalPeak Corp — Financial Performance Dashboard | 2013-2014 | V1: P & L CATEGORY X AMOUNT
B3: Gross Sales | E3: Net Sales | H3: Total Profit | K3: Profit Margin | N3: Total COGS | Q3: Units Sold | V3: P&L Category | W3: Amount | Y3: YEAR | Z3: NET SALES
B4: =KPI_SUMMARY!D4 -> 1.279316e+08 | E4: =KPI_SUMMARY!D6 -> 1.1872635e+08 | H4: =KPI_SUMMARY!D8 -> 16893702 | K4: =KPI_SUMMARY!D9 -> 0.14229109 | N4: =KPI_SUMMARY!D7 -> 101832648 | Q4: =KPI_SUMMARY!D10 -> 1125806 | V4: Gross Sales | W4: =KPI_SUMMARY!D4 -> 1.279316e+08 | Y4: 2013 | Z4: =KPI_SUMMARY!C46 -> 26415256
V5: Discounts | W5: =-KPI_SUMMARY!D5 -> -9205248.2 | Y5: 2014 | Z5: =KPI_SUMMARY!C47 -> 92311095
V6: Net Sales | W6: =KPI_SUMMARY!D6 -> 1.1872635e+08
V7: COGS | W7: =-KPI_SUMMARY!D7 -> -101832648
V8: Profit | W8: =KPI_SUMMARY!D8 -> 16893702

Sheet INSIGHTS
B1: GlobalPeak Corp — Financial Analytics Key Insights Report
C4: EXECUTIVE SUMMARY
C5: GlobalPeak Corp generated $118.7M in Net Sales (2013-2014) with a 14.23% profit margin on $127.9M gross revenue. Government segment dominates with 44.2% of total sales ($52.5M) and healthy 21.69% margin. However, Enterprise segment operates at a LOSS (-3.13% margin, -$614,546). High discounts are destroying margins — High discount band yields only 9.07% vs Low band's 17.87%. Paseo is the star product with $33M sales and $4.8M profit. Immediate action needed on Enterprise segment pricing and discount policy.
C7: 🔴 CRITICAL FINDINGS (Immediate Action Required)
C8: Finding | D8: Value | E8: Action
C9: Enterprise Segment LOSS | D9: (3.13 % margin) | E9: Review pricing strategy
C10: High Discount = Low Margin | D10: 9.07% only | E10: Cap high discounts
C11: COGS = 85.8% of Sales | D11: $101.8M | E11: Reduce production costs
C12: 2013 only 4 months data | D12: Partial year | E12: Need full year comparison
C14: 🟠 WARNING SIGNALS (Monitor Closely)
C15: Signal | D15: Value | E15: Note
C16: Small Business margin | D16: 0.0977 | E16: Below Benchmark
C17: USA lowest margin | D17: 0.1197 | E17: Despite being biggest market
C18: Medium discount margin | D18: 0.1439 | E18: Declined Trend
C20: 🟢 POSITIVE FINDINGS (What's Working Well)
C21: Finding | D21: Value | E21: Insight
C22: Government segment | D22: 44.2% revenue, 21.69% margin | E22: Start segment
C23: Channel Partners margin | D23: 0.7313 | E23: Most efficient
C24: Paseo product | D24: $33M sales, $4.8M profit | E24: Star product
C25: Low discount margin | D25: 0.1787 | E25: Best discount strategy
C26: Germany best margin | D26: 0.1566 | E26: Top Country
C28: 💡 STRATEGIC RECOMMENDATIONS
C29: Recommendation | D29: Priority | E29: Impact
C30: Fix Enterprise pricing | D30: HIGH | E30: Stop Losses
C31: Cap High discount band | D31: HIGH | E31: Margin +5 %
C32: Reduce COGS | D32: HIGH | E32: Margin Improvement
C33: Expand Government segment | D33: MEDIUM | E33: Best Margin Segment
C34: Replicate Germany strategy in USA | D34: MEDIUM | E34: USA margin up
C35: Push Paseo in all markets | D35: LOW | E35: Revenue growth
C37: 📊 LIVE KPI METRICS (Auto-updates with data)
C38: Metric | D38: Formula
C39: Gross Sales | D39: =KPI_SUMMARY!D4 -> 1.279316e+08
C40: Total Discounts | D40: =KPI_SUMMARY!D5 -> 9205248.2
C41: Net Sales | D41: =KPI_SUMMARY!D6 -> 1.1872635e+08
C42: Total COGS | D42: =KPI_SUMMARY!D7 -> 101832648
C43: Total Profit | D43: =KPI_SUMMARY!D8 -> 16893702
C44: Profit Margin | D44: =KPI_SUMMARY!D9 -> 0.14229109
C45: Total Units | D45: =KPI_SUMMARY!D10 -> 1125806
